findstring/__init__.py
findstring/__main__.py
findstring/entry.py
findstring/findstring.py
findstring/grep.py
findstring/search.py
findstring/show.py
findstring-1.0.0.dist-info/licenses/LICENSE
findstring-1.0.0.dist-info/METADATA
findstring-1.0.0.dist-info/WHEEL
findstring-1.0.0.dist-info/entry_points.txt
findstring-1.0.0.dist-info/top_level.txt
findstring-1.0.0.dist-info/RECORD
